Workbook
Name Competencies: #REF!
Name Department: 'Cover Page'!$AO$6:$AO$11

Sheet Cover Page
AN1: Department | AO1: Job Family | AQ1: Country | AR1: Company
A2: Performance Management Sheet | AR2: Karm Holding
AN3: CEO Office | AQ3: Egypt | AR3: Al Karm for Buildings
H4: Review Date | I4: From | K4: To | AN4: Logistics | AQ4: UK | AR4: Al Karm for Selling & Distribution Electricity
AN5: Finance | AQ5: NL | AR5: Sahl Hasheesh for Solar Energy
C6: Employee Name | I6: Direct Manager | AN6: HR & Admin | AQ6: Cyprus | AR6: Mars for Electricity & Distribution
AN7: Generation | AQ7: Tunisia | AR7: Saturn
C8: Position | I8: Position | AN8: O&M Office | AQ8: UAE | AR8: Mercury for Selling and Distributing Electricity
AN9: Business Development | AR9: Venus for Selling and Distributing Electricity
C10: Department | I10: Date of Hire | AN10: Investment | AR10: Andromeda Solar Works
AN11: KB - Construction | AR11: Jupiter for Selling and Distributing Electricity
C12: Senior Manager | I12: Company | AN12: Management | AR12: Al Karm for Water
AN13: Distribution | AR13: Al Karm for Buildings
C14: Country | AN14: KB- KAL | AO14: Top Management | AR14: Al Karm for Charging Electric Vehicles
AN15: Procurment | AO15: Middle Management | AR15: UK Entity
D16: Job Family | AN16: Technical Office | AO16: Staff | AR16: NL Entity
AN17: Compliance | AO17: Blue Collar - Technicians | AR17: Sarapis Energy
AN18: Digital Transformation | AR18: Sand
AN19: Legal Affairs
AN20: Operations
AN21: HSE
AN22: Sand

Sheet Objectives Setting
A1: KEY OBJECTIVES SETTING
AQ2: Core Competency | AR2: Functional Competency | AS2: Core Competency | AT2: Functional Competency | AV2: Job Family | AW2: Compliance Objective | AX2: Measurement
A3: This section establishes the objectives and commintments for the next 12 months, The manager and the employee should keep a copy of this page to refer to throughout the year. | AP3: Top Management | AQ3: Accuracy & Attention to Detail | AR3: Contribution to Other Functions Development | AS3: الدقة والاهتمام بالتفاصيل | AT3: المساهمة فى تطوير الإدارات الأخرى | AV3: Top Management | AW3: Finalize all departments’ functional policies and close compliance audit actions | AX3: Respond and finalize policies within 2 weeks of receipt; Close 95% of compliance audit actions
AP4: Top Management | AQ4: Compliance Management | AR4: Strategic Thinking & Decision Making | AS4: الالتزام بالنظم والقوانين | AT4: التخطيط الاستراتيجى واتخاذ القرار | AV4: Middle Management | AW4: Training, awareness, and implementation of launched compliance systems and policies | AX4: Pass training tests with score ≥ 85%; Zero policy breaches
A5: S | C5: Objective(s) | J5: Measure | L5: Weight | M5: Due Date | AP5: Top Management | AQ5: Continuous Learning & Self Development | AR5: Budgeting & Forcasting | AS5: التطوير الشخصى | AT5: التخطيط والموازنة | AV5: Staff | AW5: Attend all trainings and events reporting | AX5: Pass training tests with score ≥ 75%; Report 3 events/violations per month
A6: 1 | AP6: Top Management | AQ6: Results Orientation | AS6: الاهتمام بالنتائج | AV6: Blue Collar - Technicians | AW6: Attend all trainings and events reporting | AX6: Pass training tests with score ≥ 75%; Report 3 events/violations per month
A7: 2 | AP7: Top Management | AQ7: Technical Passion & Drive | AS7: المهارات الفنية
A8: 3 | AP8: Middle Management | AQ8: Accuracy & Attention to Detail | AR8: Analysis & Pattern Recognition | AS8: الدقة والاهتمام بالتفاصيل | AT8: التحليل والتعرف على الأنماط | AV8: Job Family | AW8: HSE Objective | AX8: Measures
A9: 4 | AP9: Middle Management | AQ9: Compliance Management | AR9: Delegation & People Management and Development | AS9: الالتزام بالنظم والقوانين | AT9: تطوير وتفويض وتحفيز العاملين | AV9: Top Management | AW9: Ensure leadership commitment to HSE compliance, governance, and visible safety leadership. | AX9: • 100% attendance in HSES trainings• 100% attendance in HSES meetings• Complete 4 HSES observations• Conduct 2 management safety tours• Zero verbal or written HSE warnings
A10: 5 | AP10: Middle Management | AQ10: Continuous Learning & Self Development | AR10: Leadership | AS10: التطوير الشخصى | AT10: القدرات القيادية | AV10: Middle Management | AW10: Ensure effective implementation, monitoring, and enforcement of HSE systems and policies within teams. | AX10: • 100% attendance in HSES trainings• 100% attendance in HSES meetings• Complete 4 HSES observations• Conduct 2 management safety tours• Close 100% of critical and 80% of other audit actions• Zero verbal or written HSE warnings
A11: 6 | C11: {=_xlfn.IFS(B20="Top Management","Ensure leadership commitment to HSE compliance, governance, and visible safety leadership.",B20="Middle Management","Ensure effective implementation, monitoring, and enforcement of HSE systems and policies within teams.",B20="Staff","Comply with HSE requirements and actively contribute to a safe and compliant working environment.",B20="Blue Collar - Technicians","Adhere to HSE procedures and actively participate in maintaining a safe work environment.")} -> #N/A | J11: {=_xlfn.IFS(B20="Top Management","100% HSES trainings; 100% HSES meetings; 4 observations; 2 management tours; Zero warnings",B20="Middle Management","100% HSES trainings; 100% HSES meetings; 4 observations; 2 management tours; 100% critical & 80% other audit actions; Zero warnings",B20="Staff","100% HSES trainings; 100% HSES meetings; 12 observations; close 100% critical & 80% other audit actions; Zero warnings",B20="Blue Collar - Technicians","100% HSES trainings; 100% HSES meetings; 12 observations; Zero warnings")} -> #N/A | L11: 0.1 | AP11: Middle Management | AQ11: Results Orientation | AS11: الاهتمام بالنتائج | AV11: Staff | AW11: Comply with HSE requirements and actively contribute to a safe and compliant working environment. | AX11: • 100% attendance in HSES trainings• 100% attendance in HSES meetings• Submit 12 HSES observations• Close 100% of critical and 80% of other assigned audit actions• Zero verbal or written HSE warnings
A12: 7 | C12: {=_xlfn.IFS(B20="Top Management","Finalize all departments’ functional policies and close compliance audit actions",B20="Middle Management","Training, awareness, and implementation of launched compliance systems and policies",OR(B20="Staff",B20="Blue Collar - Technicians"),"Attend all trainings and events reporting")} -> #N/A | J12: {=_xlfn.IFS(B20="Top Management","Respond and finalize policies within 2 weeks of receipt; Close 95% of compliance audit actions", B20="Middle Management","Pass training tests with score ≥ 85%; Zero policy breaches",OR(B20="Staff",B20="Blue Collar - Technicians"),"Pass training tests with score ≥ 75%; Report 3 events/violations per month")} -> #N/A | L12: =IF(B20="Top Management",10%,5%) -> 0.05 | AP12: Middle Management | AQ12: Technical Passion & Drive | AS12: المهارات الفنية | AV12: Blue Collar | AW12: Adhere to HSE procedures and actively participate in maintaining a safe work environment. | AX12: • 100% attendance in HSES trainings• 100% attendance in HSES meetings• Submit 12 HSES observations• Zero verbal or written HSE warnings
A13: Total Weight | L13: =SUM(L6:L12) -> 0.15 | M13: =IF(OR(L13=0,L13=100%),"","Error") -> Error | AP13: Staff | AQ13: Accuracy & Attention to Detail | AR13: Creativity & Innovation | AS13: الدقة والاهتمام بالتفاصيل | AT13: القدرة على الإبداع والابتكار
AP14: Staff | AQ14: Compliance Management | AR14: Problem Solving | AS14: الالتزام بالنظم والقوانين | AT14: القدرة على حل المشاكل
A15: Date of Last Review | I15: Last Review Objectives Score | AP15: Staff | AQ15: Continuous Learning & Self Development | AR15: Initiative | AS15: التطوير الشخصى | AT15: المبادرة
A16: Competencies Scale Definition | D16: Beginner | G16: Developing | I16: Competent | K16: Advanced | L16: Expert | AP16: Staff | AQ16: Results Orientation | AS16: الاهتمام بالنتائج
D17: 1 | G17: 2 | I17: 3 | K17: 4 | L17: 5 | AP17: Staff | AQ17: Technical Passion & Drive | AS17: المهارات الفنية
AP18: Blue Collar - Lead | AQ18: Accuracy & Attention to Detail | AR18: Problem Solving | AS18: الدقة والاهتمام بالتفاصيل | AT18: القدرة على حل المشاكل
C19: Core Competencies | I19: المهارات الرئيسية | L19: Rating | M19: Avg Rating | AP19: Blue Collar - Lead | AQ19: Compliance Management | AR19: Initiative | AS19: الالتزام بالنظم والقوانين | AT19: المبادرة
A20: 1 | B20: ='Cover Page'!$H$16 -> 0 | C20: Knowledge | D20: Excellence | I20: المعرفة | K20: التميز | L20: 3 | M20: =AVERAGE(L20:L21) -> 3 | AP20: Blue Collar - Lead | AQ20: Continuous Learning & Self Development | AR20: Product Knoweledge | AS20: التطوير الشخصى | AT20: المعرفة التامة بمنتجات الشركة
B21: ='Cover Page'!$H$16 -> 0 | D21: Success | K21: النجاح | L21: 3 | AP21: Blue Collar - Lead | AQ21: Results Orientation | AS21: الاهتمام بالنتائج
A22: 2 | B22: ='Cover Page'!$H$16 -> 0 | C22: Attitude | D22: Collaboration and Care | I22: السلوك | K22: التعاون والتراحم | L22: 3 | M22: =AVERAGE(L22:L23) -> 3 | AP22: Blue Collar - Lead | AQ22: Technical Passion & Drive | AS22: المهارات الفنية
A23: 4 | B23: ='Cover Page'!$H$16 -> 0 | C23: =IF(B23="Top Management",VLOOKUP(B23,AP6:AQ10,2,0),IF(B23="Middle Management",VLOOKUP(B23,AP11:AQ15,2,0),IF(B23="Staff",VLOOKUP(B23,AP16:AQ20,2,0),IF(B23="Blue Collar - lead",VLOOKUP(B23,AP21:AQ25,2,0),IF(B23="Blue Collar - Technicians",VLOOKUP(B23,AP27:AQ31,2,0),0))))) -> 0 | D23: Accountability | K23: تحمل المسؤولية | L23: 3 | AP23: Blue Collar - Technicians | AQ23: Accuracy & Attention to Detail | AR23: Problem Solving | AT23: القدرة على حل المشاكل
A24: 3 | B24: ='Cover Page'!$H$16 -> 0 | C24: Feedback | D24: Respect | I24: تقبل النقد | K24: الاحترام | L24: 3 | M24: =AVERAGE(L24:L25) -> 3 | AP24: Blue Collar - Technicians | AQ24: Compliance Management | AR24: Initiative | AT24: المبادرة
D25: Learner Mindset | K25: عقلية التعلم | L25: 3 | AP25: Blue Collar - Technicians | AQ25: Continuous Learning & Self Development | AR25: Product Knoweledge | AT25: المعرفة التامة بمنتجات الشركة
C26: Functional Competencies | I26: المهارات الوظيفية | M26: Rating | AQ26: Results Orientation | AS26: الاهتمام بالنتائج
A27: 4 | B27: ='Cover Page'!$H$16 -> 0 | C27: =IF(B27="Top Management",VLOOKUP(B27,AP3:AR7,3,0),IF(B27="Middle Management",VLOOKUP(B27,AP8:AR12,3,0),IF(B27="Staff",VLOOKUP(B27,AP13:AR17,3,0),IF(B27="Blue Collar",VLOOKUP(B27,AP18:AR22,3,0),IF(B27="Blue Collar - Technicians",VLOOKUP(B27,AP23:AR28,3,0),0))))) -> 0 | I27: =IF(B27="Top Management",VLOOKUP(B27,AP3:AT7,5,0),IF(B27="Middle Management",VLOOKUP(B27,AP8:AT12,5,0),IF(B27="Staff",VLOOKUP(B27,AP13:AT17,5,0),IF(B27="Blue Collar - Lead",VLOOKUP(B27,AP18:AT22,5,0),IF(B27="Blue Collar - Technicians",VLOOKUP(B27,AP23:AT28,5,0),0))))) -> 0 | M27: 3 | AP27: Blue Collar - Technicians | AQ27: Technical Passion & Drive | AS27: المهارات الفنية
A28: 5 | B28: ='Cover Page'!$H$16 -> 0 | C28: =IF(B28="Top Management",VLOOKUP(B28,AP4:AR8,3,0),IF(B28="Middle Management",VLOOKUP(B28,AP9:AR13,3,0),IF(B28="Staff",VLOOKUP(B28,AP14:AR18,3,0),IF(B28="Blue Collar",VLOOKUP(B28,AP19:AR23,3,0),IF(B28="Blue Collar - Technicians",VLOOKUP(B28,AP24:AR29,3,0),0))))) -> 0 | I28: =IF(B28="Top Management",VLOOKUP(B28,AP4:AT8,5,0),IF(B28="Middle Management",VLOOKUP(B28,AP9:AT13,5,0),IF(B28="Staff",VLOOKUP(B28,AP14:AT18,5,0),IF(B28="Blue Collar - Lead",VLOOKUP(B28,AP19:AT23,5,0),IF(B28="Blue Collar - Technicians",VLOOKUP(B28,AP24:AT29,5,0),0))))) -> 0 | M28: 3 | AP28: Blue Collar - Technicians
A29: 6 | B29: ='Cover Page'!$H$16 -> 0 | C29: =IF(B29="Top Management",VLOOKUP(B29,AP5:AR9,3,0),IF(B29="Middle Management",VLOOKUP(B29,AP10:AR14,3,0),IF(B29="Staff",VLOOKUP(B29,AP15:AR19,3,0),IF(B29="Blue Collar - lead",VLOOKUP(B29,AP20:AR24,3,0),IF(B29="Blue Collar - Technicians",VLOOKUP(B29,AP25:AR30,3,0),0))))) -> 0 | I29: =IF(B29="Top Management",VLOOKUP(B29,AP5:AT9,5,0),IF(B29="Middle Management",VLOOKUP(B29,AP10:AT14,5,0),IF(B29="Staff",VLOOKUP(B29,AP15:AT19,5,0),IF(B29="Blue Collar - Lead",VLOOKUP(B29,AP20:AT24,5,0),IF(B29="Blue Collar - Technicians",VLOOKUP(B29,AP25:AT30,5,0),0))))) -> 0 | M29: 3
A31: ADDITIONAL COMMENTS
A32: EMPLOYEE | I32: DIRECT MANAGER
A39: Employee | F39: Position | K39: Signature | M39: Date
A40: ='Cover Page'!AW5 -> 0 | F40: ='Cover Page'!AX5 -> 0
A41: Direct Manager | F41: Position | K41: Signature | M41: Date
A42: ='Cover Page'!AW6 -> 0 | F42: ='Cover Page'!AW7 -> 0

Sheet Performance Review
A1: PERFORMANCE REVIEW
A2: Based on the agreed objectives from the last appraisal, the manager and employee should make an informed and objective evaluation of the performance against each objective.
A6: # | B6: Objectives | E6: Measure | J6: Weight | L6: Score | M6: Wt Score | N6: Comments
A7: 1 | B7: ='Objectives Setting'!C6 -> 0 | E7: ='Objectives Setting'!J6 -> 0 | J7: ='Objectives Setting'!L6 -> 0 | M7: =J7*L7 -> 0 | U7: =88%*40% -> 0.352
A8: 2 | B8: ='Objectives Setting'!C7 -> 0 | E8: ='Objectives Setting'!J7 -> 0 | J8: ='Objectives Setting'!L7 -> 0 | M8: =J8*L8 -> 0
A9: 3 | B9: ='Objectives Setting'!C8 -> 0 | E9: ='Objectives Setting'!J8 -> 0 | J9: ='Objectives Setting'!L8 -> 0 | M9: =J9*L9 -> 0
A10: 4 | B10: ='Objectives Setting'!C9 -> 0 | E10: ='Objectives Setting'!J9 -> 0 | J10: ='Objectives Setting'!L9 -> 0 | M10: =J10*L10 -> 0
A11: 5 | B11: ='Objectives Setting'!C10 -> 0 | E11: ='Objectives Setting'!J10 -> 0 | J11: ='Objectives Setting'!L10 -> 0 | M11: =J11*L11 -> 0
A12: 6 | B12: ='Objectives Setting'!C11 -> #N/A | E12: ='Objectives Setting'!J11 -> #N/A | J12: ='Objectives Setting'!L11 -> 0.1 | M12: =J12*L12 -> 0
A13: 7 | B13: ='Objectives Setting'!C12 -> #N/A | E13: ='Objectives Setting'!J12 -> #N/A | J13: ='Objectives Setting'!L12 -> 0.05 | M13: =J13*L13 -> 0
A14: 8 | B14: ='Objectives Setting'!AE13 -> 0 | E14: ='Objectives Setting'!#REF! -> #REF! | J14: ='Objectives Setting'!#REF! -> #REF! | M14: =L14*J14 -> #REF!
A15: Total | M15: =ROUNDDOWN(SUM(M7:M13),2) -> 0
D16: Performance Status | M16: =VLOOKUP(M15,'Sucession Plan Score'!I:J,2) -> #N/A
A17: Last Period | M17: ='Objectives Setting'!L15 -> 0
A19: Competencies Scale Definition | D19: Beginner | E19: Developing | H19: Competent | I19: Advanced | J19: Expert
D20: 1 | E20: 2 | H20: 3 | I20: 4 | J20: 5
A22: # | B22: Core Competencies | H22: المهارات رئيسية للوظيفية | L22: Required Rating | M22: Actual Rating | N22: Comments
A23: 1 | B23: ='Objectives Setting'!AS32 -> 0 | D23: ='Objectives Setting'!D20 -> Excellence | H23: ='Objectives Setting'!AU35 -> 0 | I23: ='Objectives Setting'!K20 -> التميز | L23: ='Objectives Setting'!L20 -> 3
D24: ='Objectives Setting'!D21 -> Success | I24: ='Objectives Setting'!K21 -> النجاح | L24: ='Objectives Setting'!L21 -> 3
A25: 2 | B25: ='Objectives Setting'!AS34 -> 0 | D25: ='Objectives Setting'!D22 -> Collaboration and Care | H25: ='Objectives Setting'!AU37 -> 0 | I25: ='Objectives Setting'!K22 -> التعاون والتراحم | L25: ='Objectives Setting'!L22 -> 3
D26: ='Objectives Setting'!D23 -> Accountability | I26: ='Objectives Setting'!K23 -> تحمل المسؤولية | L26: ='Objectives Setting'!L23 -> 3
A27: 3 | B27: ='Objectives Setting'!AS36 -> 0 | D27: ='Objectives Setting'!D24 -> Respect | H27: ='Objectives Setting'!AU39 -> 0 | I27: ='Objectives Setting'!K24 -> الاحترام | L27: ='Objectives Setting'!L24 -> 3
A28: 6 | D28: ='Objectives Setting'!D25 -> Learner Mindset | I28: ='Objectives Setting'!K25 -> عقلية التعلم | L28: ='Objectives Setting'!L25 -> 3
B29: Functional Competencies | H29: المهارات ثانوية للوظيفية | L29: Required Rating | M29: Actual Rating | N29: Comments
A30: 4 | B30: ='Objectives Setting'!AS38 -> 0 | H30: ='Objectives Setting'!AU41 -> 0 | L30: ='Objectives Setting'!M27 -> 3
A31: 5 | B31: ='Objectives Setting'!AS39 -> 0 | H31: ='Objectives Setting'!AU42 -> 0 | L31: ='Objectives Setting'!M28 -> 3
A32: 6 | B32: ='Objectives Setting'!AS40 -> 0 | H32: ='Objectives Setting'!AU43 -> 0 | L32: ='Objectives Setting'!M29 -> 3
A33: Average Competencies Rating | M33: =AVERAGE(M23:M28,M30:M32) -> #DIV/0!
A34: Total Evaluation Score | M34: =M15+(IF(AND(M33>=1,M33<=1.9),"-10%",IF(AND(M33>=2,M33<=2.9),"-5%",IF(AND(M33>=3,M33<=3.9),"0%",IF(AND(M33>=4,M33<=4.9),"5%",IF(AND(M33>=5,M33<=5.9),"10%")))))) -> #DIV/0!
D35: Potential Status | M35: =VLOOKUP(M33,'Sucession Plan Score'!L:M,2) -> #DIV/0!
C36: Sucession Planning Status | M36: =VLOOKUP(M35,'Sucession Plan Score'!R:S,2,0) -> #DIV/0!
A37: GENERAL ADDITIONAL COMMENTS
A38: EMPLOYEE | J38: Direct Manager

Sheet Sucession Plan Score
D1: Performance | E1: Potential | F1: 9 Box Grid | I1: Score | J1: Record | L1: Score | M1: Record | Q1: {=_xlfn._xlws.FILTER(D:F,D:D='Performance Review'!M16,0)} -> #N/A
D2: High | E2: High | F2: Top Talent | I2: 0.6 | J2: Low | L2: 2 | M2: Low
D3: Medium | E3: High | F3: High Potential | I3: 0.61 | J3: Low | L3: 2.1 | M3: Low
D4: Low | E4: High | F4: Potential Star | I4: 0.62 | J4: Low | L4: 2.2 | M4: Low
D5: High | E5: Medium | F5: High Performer | I5: 0.63 | J5: Low | L5: 2.3 | M5: Low
D6: Medium | E6: Medium | F6: Core Player | I6: 0.64 | J6: Low | L6: 2.4 | M6: Low
D7: Low | E7: Medium | F7: Potential Performer | I7: 0.65 | J7: Low | L7: 2.5 | M7: Low
D8: High | E8: Low | F8: Solid Performer | I8: 0.66 | J8: Low | L8: 2.6 | M8: Low
D9: Medium | E9: Low | F9: Average Performer | I9: 0.67 | J9: Low | L9: 2.7 | M9: Low
D10: Low | E10: Low | F10: Under Performer | I10: 0.68 | J10: Low | L10: 2.8 | M10: Low
I11: 0.69 | J11: Low | L11: 2.9 | M11: Low
I12: 0.7 | J12: Low | L12: 3 | M12: Medium
I13: 0.71 | J13: Low | L13: 3.1 | M13: Medium
I14: 0.72 | J14: Low | L14: 3.2 | M14: Medium
I15: 0.73 | J15: Low | L15: 3.3 | M15: Medium
I16: 0.74 | J16: Low | L16: 3.4 | M16: Medium
I17: 0.75 | J17: Low | L17: 3.5 | M17: Medium
I18: 0.76 | J18: Low | L18: 3.6 | M18: Medium
I19: 0.77 | J19: Low | L19: 3.7 | M19: Medium
I20: 0.78 | J20: Low | L20: 3.8 | M20: Medium
I21: 0.79 | J21: Low | L21: 3.9 | M21: Medium
I22: 0.8 | J22: Medium | L22: 4 | M22: High
... I32: 0.9 | J32: High | L32: 5 | M32: High
I33: 0.91 | J33: High
I34: 0.92 | J34: High
I35: 0.93 | J35: High
I36: 0.94 | J36: High
I37: 0.95 | J37: High
I38: 0.96 | J38: High
I39: 0.97 | J39: High
I40: 0.98 | J40: High
I41: 0.99 | J41: High
I42: 1 | J42: High
I43: 1.01 | J43: High
I44: 1.02 | J44: High
... I51: 1.09 | J51: High

Sheet Sheet1
A1: COMPETENCIES | D1: DEFINITION
A2: Core | B2: Accuracy & Attention to Detail | C2: الدقة والاهتمام بالتفاصيل | D2: Measures the ability to pay attention to details, minimize errors, keep tasks clear and on schedule to ensure error-free results
A3: Core | B3: Compliance Management | C3: الالتزام بالنظم والقوانين | D3: Measures the ability to establish and apply guidelines, policies and procedures in order to ensure consistency and allow for improvement
A4: Core | B4: Continuous Learning & Self Development | C4: التطوير الشخصى | D4: Measures the willingness and the steps taken for self development
A5: Core | B5: Results Orientation | C5: الاهتمام بالنتائج | D5: Measures the ability to set/ achieve clear goals and objectives, follows up on tasks until completed, takes responsibility to resolve issues that may threaten delivery
A6: Core | B6: Technical Passion & Drive | C6: المهارات الفنية | D6: Measures the ability to learn, integrate and use new work-related knowledge and expertise to reach maximum potential for self development
A7: Top Management | B7: Contribution to Other Functions Development | C7: المساهمة فى تطوير الإدارات الأخرى | D7: Measures how much the manager contributes to the improvement and development of other functions/ Inter-departmental cooperation
A8: Top Management | B8: Strategic Thinking & Decision Making | C8: التخطيط الاستراتيجى واتخاذ القرار | D8: Measures the ability to see ahead clearly with a future business outlook, anticipate future conesquences and trends, be future oriented, picture the organization as a whole and the relationship among various parts
A9: Top Management | B9: Financial Management
A10: Middle Management | B10: Analysis & Pattern Recognition | C10: التحليل والتعرف على الأنماط | D10: Measures the ability to gather & examine information, facts, and data, identify a pattern, generalize from specifics, itegrate discrete data into coherent whole
A11: Middle Management | B11: Delegation & People Management | C11: تطوير وتفويض وتحفيز العاملين | D11: Measures how the manager deals with second line managers: delegation, motivation, turn over rate, training,…
A12: Middle Management | B12: Leadership | C12: القدرات القيادية | D12: Measures the ability to lead/ solve problems/ resolve conflicts/ take decisisons
A13: Staff | B13: Creativity & Innovation | C13: القدرة على الإبداع والابتكار | D13: Measure the ability of an employee to generate new ideas and develop existing ones into workable solutions, and also the ability to develop or improves existing systems
A14: Staff | B14: Problem Solving | C14: القدرة على حل المشاكل | D14: Measures the ability to organize and analyze information, identify solutions, and implement the most appropriate | E14: Blue Collar - Lead
A15: Staff | B15: Teamwork | C15: العمل الجماعى | D15: Measures the ability to work well within a team, communicate efficiently both in writing and verbally, leverages knowledge, listens carefully, helps resolve team conflicts, and cooperate | E15: Blue Collar - both
B16: Approachability | C16: القدرة على الاستماع والتقرب من الآخرين بسهولة | D16: Measures the ability to approach others in a warm and friendly manner, builds rapport well, a good listener
B17: Communication Skills | C17: القدرة على التواصل | D17: Measures the ability to communicate with peers/ subordinates/ clients/ managers… and reach constructive results
B18: Continuous Improvement | C18: التطوير المستمر | D18: Measures how the manager deals with opportunities of improvement/ how many times through the period the manager proposed and implemented change or development in processes
B19: Customer Focus | C19: الاهتمام بالعميل | D19: Measures the ability to meet and/or exceed customer expectations, operate with customer interest in mind, gain customer trust and loyalty
B20: General Appearance | C20: المظهر العام | D20: Measures how professional the employees looks, general appearance
B21: Initiative | C21: المبادرة | D21: Measures the ability to be proactive, take appropriate action without being asked, work with minimum directions, take responsibility | E21: Blue Collar - Tech
B22: Negotiation Skills | C22: المهارات التفاوضية | D22: Measures the ability to negotiate skillfully in tough situations both internally and externally, reach accpetable results, without damaging relationships
B23: Networking | C23: القدرة على تكوين شبكة اتصالات | D23: Measures the ability to see and capture opportunities, build networks of formal and informal relationships, have a good business sense
B24: Product Knoweledge | C24: المعرفة التامة بمنتجات الشركة | D24: Measures employee knoweldge of all product details, and completing product training requested
B25: Reporting | C25: أصدار التقارير فى الوقت المناسب بالكفاءة المطلوبة | D25: Reporting on time | E25: Blue Collar - Lead

Sheet Succession Planning
A1: 9 Box Grid- Succession Planning
G5: Description | V5: Action Plan
A6: Potential / Comptencies | B6: High | C6: 4 - 5 | D6: Potential Star -High Potential/ Low Performer -Role model in their current function -Inconsistent Performance and expectations are not yet fully being met. | G6: High Potential -High Potential/ Medium Performance -Goals are frequently met and potential is demonstrated in new and challengingg situations. -Role model in current function -Consistently delivers extraordinary results | J6: Top Talent - High Potential/ High Performance -Exceeds or Outstanding performance -Role Model across the organization -Promotable now | P6: Potential / Comptencies | Q6: High | R6: 4 - 5 | S6: Potential Star -Communicate your expectation -Monitor Performance for a year -No Improvement- Exit Plan | V6: High Potential | Y6: Top Talent Ready Now
B12: Medium | C12: 3 - 3.9 | D12: Potential Performer -Medium Potential/ Low Performance -Still new in current role and not yet performing all duties -Expectations are not being met yet -Performance is not consistent or declining | G12: Core Player -Medium Potential/ Medium Performance -Meets performance expectations and there is high potential for increased responsibilities. Adapt quickly to change. -Capable of growing into a more complex role -May be promotable outside of current level | J12: High Performer -Medium Potential/ High Performance -Strong Performer and consistently meeting or exceeding expectations. Has capability to grow into a more complex role. | Q12: Medium | R12: 3 - 3.9 | S12: Potential Performer -Training & Improvement Plan -Check performance every Month for 6 Month to 1 year -No Improvement - Exit Plan | V12: Core Player | Y12: High Performer 1-2 Years to Next step
B19: Low | C19: 2 -2.9 | D19: Under Performer -Low Performance/ Low Potential -Does not meet/partially meets performance expectations -May not be a fit for current role | G19: Average Performer -Low Potential/Low Performance -Good fit for current role and consistently provide value, but may lack interest to move to a higher position. | J19: Solid Performer -Low Potential/ High Performance -Provide significant value in current role but not likely to move to a higher level. | Q19: Low | R19: 2 -2.9 | S19: Under Performer Exit Plan | V19: Average Performer -Training & Improvement Plan -Check performance every Month for 6 Month to 1 year -No Improvement - Exit Plan | Y19: Solid Performer -Communicate you expectation -Monitor Performance for a year -No Improvement- Exit Plan
D25: 60 % - 79% | G25: 80% - 89% | J25: 90% - Above | S25: 60 % - 79% | V25: 80% - 89% | Y25: 90% - Above
D26: Low | G26: Medium | J26: High | S26: Low | V26: Medium | Y26: High
D27: Performance | S27: Performance
D46: ='Performance Review'!M36 -> #DIV/0! | G46: =D46 -> #DIV/0! | J46: =G46 -> #DIV/0!
D52: =J46 -> #DIV/0! | G52: =D52 -> #DIV/0! | J52: =G52 -> #DIV/0!
D59: =J52 -> #DIV/0! | G59: =D59 -> #DIV/0! | J59: =G59 -> #DIV/0!

Sheet Development Plan
A2: DEVELOPMENT PLAN
A4: CAREER PLANNING
A5: Short Term | D5: Long Term
A12: LEARNING & DEVELOPMENT PLAN
A13: Improvement Area's (if any) | D13: Action
A20: ADDITIONAL COMMENTS
A21: EMPLOYEE | D21: DIRECT MANAGER
A28: TRAINING & DEVELOPMENT SECTION
A29: Number | B29: Training Course | D29: Institute or Source | G29: Preferred Date
A30: 1
A31: 2
A32: 3
A33: 4

Sheet Core Competencies Def.
D2: Beginner | E2: Developing | F2: Competent | G2: Advanced | H2: Expert
B3: Knowledge | C3: Excellence. Excellence is not a goal—it is a standard. We take pride in fully understanding our areas of expertise that reflects on providing high quality work to our internal and external clients. | D3: Understands the basic requirements of the role. Seeks guidance to ensure work meets minimum quality standards. | E3: Consistently applies technical knowledge to tasks. Begins to identify and correct own errors before submission. | F3: Fully masters the scope of work. Delivers high-quality results autonomously that meet or exceed client expectations. | G3: Anticipates quality issues before they arise. Streamlines processes to improve efficiency without sacrificing quality. | H3: Sets the "gold standards" for the Company and produces new knowledge in the subject matter Recognized as a Subject Matter Expert (SME) who mentors others in mastery.
C4: Success. Our success is to deliver quality work that ensures solid financial growth and continuous development of state-of-the-art technology in our field of expertise. | D4: Completes assigned tasks on time. Understands how their specific role contributes to the team’s goals. | E4: Suggests small improvements to save time or resources. Shows awareness of the firm’s financial objectives. | F4: Delivers work that directly contributes to project profitability or technological uptime. Balances quality with speed effectively. | G4: Identifies new opportunities for cost-saving or revenue generation. Actively contributes to technological development or refinement. | H4: Orchestrates large-scale initiatives that drive significant value for the organization. Aligns technological innovation with long-term market performance including production of patents and commercializing them.
B5: Attitude | C5: Collaboration and Care. True collaboration means effective teamwork, knowledge-sharing, respecting differing viewpoints, and leveraging the strengths of our diverse teams. Pursue mentoring others | D5: Participates in meetings and shares information when asked. Maintains a decent and polite working relationships. Shows basic awareness of others’ needs. Participates in team-building activities | E5: Proactively offers help to teammates without being asked. Acknowledges different viewpoints during discussions. Supports teammates during high-pressure periods when needed. | F5: Actively shares knowledge to prevent information silos and ensure maximum benefit. Works effectively with diverse colleagues across different departments. Anticipates teammates’ needs and offers support proactively. | G5: Resolves team conflicts constructively. Builds bridges between international sites to harmonize efforts. Acts as a role model in caring leadership, mentoring others to do the same. Initiates and supports team-building activities that strengthen collaboration, engagement, and morale. | H5: Creates a culture of radical synergy. Leverages the full diversity of the workforce to solve complex multidimensional challenges. Anticipates the needs of people and the organization and acts with care through decisions that balance performance and long-term sustainability. Builds strong, high-performing teams by leading meaningful team-building initiatives and fostering sustained engagement and collaboration.
C6: Accountability. Each of us is responsible for upholding the reputation and success of Karm. while being held accountable for our results. Building a culture dependent on adhering to governance and processes, rather than trust between individuals. | D6: Follows instructions and admits mistakes when they are pointed out. Understands the criticality and importance of Karm. reputation. | E6: Takes ownership of daily tasks and shows the right level of care to deliver as per expected and agreed standards. Provides status updates without being prompted. | F6: Holds self responsible for meeting KPIs and continuously looks for short and long term solutions. Takes immediate corrective action if results deviate from the plan. | G6: Assumes responsibility for team outcomes (even if not the leader). Acts as a guardian of Karm. brand in the public eye | H6: Sets the standards for institutional integrity by playing an active role in improvement activities. Takes full ownership of high-stakes strategic risks and their consequences
B7: Feedback | C7: Respect. We act with unwavering respect, integrity, and transparency no matter the context or location. | D7: Adheres to the Karm. code of conduct. Communicates honestly with colleagues and immediate supervisors. | E7: Demonstrates sensitivity to the company culture and diversity. Maintains transparency even when delivering "bad news" or reporting errors. | F7: Pursuing a consistently ethical behavior to ensure institutional cohesion. Treats all colleagues, from site workers to executives, with equal dignity. | G7: Champions transparency in difficult situations. Protects Karm.'s integrity by calling out behaviors that contradict the company values. | H7: Embodies Karm. ethical compass represented in policies and social behavior. Creates an environment where psychological safety and transparency are the norm.
C8: Learner Mindset. We are eager for continuous learning by dealing with our daily interactions and experiences as great opportunities to learn, develop and acquire knowledge. | D8: Open to feedback and willing to attend learning sessions. Shows curiosity about Karm. activities, and the industry and countries we operate in. Attends required trainings when instructed | E8: Asks insightful questions to deepen understanding. Applies lessons learned from past mistakes to current work. Acknowledges areas for improvement when feedback is provided and participates in relevant training opportunities. | F8: Actively utilize feedback and pursues self-development Stays updated on latest solar trends and regulatory changes in countries we operate in. Actively identifies own skill gaps, seeks feedback, and requests appropriate training to improve performance. | G8: Transforms daily challenges into learning moments for the team. Rapidly adapts to new technologies, markets and businesses. Proactively drives personal development by continuously assessing strengths and weaknesses and pursuing targeted learning opportunities. | H8: Drives an "Organizational Learning" culture, encouraging colleagues to learn and leading by example. Anticipates future skill gaps and builds the systems to address them. Embeds a learner mindset into daily work, models self-development for others, and encourages a culture of continuous learning and growth.

Sheet Competencies
B1: Functional Competency | C1: مهارات الوظيفية
A2: Top Management | B2: Contribution to Other Functions Development | C2: المساهمة فى تطوير الإدارات الأخرى
B3: Strategic Thinking & Decision Making | C3: التخطيط الاستراتيجى واتخاذ القرار
B4: Budgeting & Forcasting | C4: التخطيط والموازنة
A5: Middle Management | B5: Analysis & Pattern Recognition | C5: التحليل والتعرف على الأنماط
B6: Delegation & People Management & Development | C6: تطوير وتفويض وتحفيز العاملين
B7: Leadership | C7: القدرات القيادية
A8: Staff | B8: Creativity & Innovation | C8: القدرة على الإبداع والابتكار
B9: Problem Solving | C9: القدرة على حل المشاكل
B10: Initiative | C10: المبادرة
A11: Blue Collar | B11: Problem Solving | C11: القدرة على حل المشاكل
B12: Initiative | C12: المبادرة
B13: Product Knoweledge | C13: المعرفة التامة بمنتجات الشركة

Sheet Performance Profile
A1: Performance Profile
A3: General Information
A5: Employee Name | B5: Position | C5: Department | D5: Date of Hire
A6: ='Objectives Setting'!A40:E40 -> 0 | B6: ='Cover Page'!AX5 -> 0 | C6: ='Cover Page'!AW8 -> 0 | D6: ='Cover Page'!AW10 -> 0
A7: Direct Supervisor | B7: Position | C7: Senior Manager
A8: ='Cover Page'!AW6 -> 0 | B8: ='Cover Page'!AW7 -> 0 | C8: ='Cover Page'!AW3 -> 0
A10: Total Evaluation | D10: Competency Rating Guide | G10: Total Evaluation Score | H10: Bonus Payment
A11: Ratings | D11: Ratings | G11: >100% | H11: PDR
A12: 5 Exceptional | B12: Cosistently exceeds set Targets | C12: >=95 | D12: 5 Exceptional | E12: 5 | G12: 90% - 100% | H12: 1
A13: 4 Above Expectations | B13: Always meets and sometimes exceeds set targets | C13: 90%-94% | D13: 4 Above Expectations | E13: 4-4.9 | G13: 80% - 89% | H13: 0.9
A14: 3 Meets | B14: Sometimes meets expectations | C14: 80%-89% | D14: 3 Meets | E14: 3-3.9 | G14: 70% - 79% | H14: 0.75
A15: 2 Needs Improvement | B15: Requires development to achieve the set targets | C15: 61%-79% | D15: 2 Needs Improvement | E15: 2-2.9 | G15: 60% - 69% | H15: 0.5
A16: 1 Unsatisfactory | B16: Unsatisfactory achievements of the set targets | C16: <=60% | D16: 1 Unsatisfactory | E16: Less than 2 | G16: 50% - 59% | H16: 0.25
G17: <=49% | H17: 0
A18: Performance Analysis
A19: Review Focus | B19: Total Evaluation Score | C19: Average Competencies | D19: Total KPIs
A20: Actual Score | B20: ='Performance Review'!M34 -> #DIV/0! | C20: ='Performance Review'!M33 -> #DIV/0! | D20: ='Performance Review'!M15 -> 0
A22: Rating | B22: =IF(B20<=65%,"Unsatisfactory",IF(B20=66%,"Needs Improvement",IF(B20<=79%,"Needs Improvement",IF(B20=80%,"Meets",IF(B20<=94%,"Meets",IF(B20=95%,"Above Expectations",IF(B20<=100%,"Above Expectations",IF(B20>=101%,"Exceptional",0)))))))) -> #DIV/0! | C22: =IF(C20<=1.9,"Unsatisfactory",IF(C20=2,"Needs Improvement",IF(C20<=2.9,"Needs Improvement",IF(C20=3,"Meets",IF(C20<=3.9,"Meets",IF(C20=4,"Above Expectations",IF(C20<=4.9,"Above Expectations",IF(C20>=5,"Exceptional",0)))))))) -> #DIV/0! | D22: =IF(D20<=60%,"Unsatisfactory",IF(D20=61%,"Needs Improvement",IF(D20<=79%,"Needs Improvement",IF(D20=80%,"Meets",IF(D20<=89%,"Meets",IF(D20=90%,"Above Expectations",IF(D20<=94%,"Above Expectations",IF(D20>=95%,"Exceptional",0)))))))) -> Unsatisfactory
